report_pkg/__init__.py
report_pkg/report.py
reportpkg-0.0.1.dist-info/METADATA
reportpkg-0.0.1.dist-info/WHEEL
reportpkg-0.0.1.dist-info/top_level.txt
reportpkg-0.0.1.dist-info/RECORD
